platforms.py
social_media_gif_downloader.py
social_media_gif_downloader-1.0.5.dist-info/licenses/LICENSE
social_media_gif_downloader-1.0.5.dist-info/METADATA
social_media_gif_downloader-1.0.5.dist-info/WHEEL
social_media_gif_downloader-1.0.5.dist-info/entry_points.txt
social_media_gif_downloader-1.0.5.dist-info/top_level.txt
social_media_gif_downloader-1.0.5.dist-info/RECORD
