Metadata-Version: 2.4
Name: social-media-gif-downloader
Version: 1.0.5
Summary: A GUI to download videos/GIFs from social media.
Author: ax2bboud
Project-URL: Homepage, https://github.com/ax2bboud/social-media-gif-downloader
Project-URL: Repository, https://github.com/ax2bboud/social-media-gif-downloader
Project-URL: Issues, https://github.com/ax2bboud/social-media-gif-downloader/issues
Classifier: Development Status :: 4 - Beta
Classifier: Intended Audience :: End Users/Desktop
Classifier: License :: OSI Approved :: MIT License
Classifier: Programming Language :: Python :: 3
Classifier: Programming Language :: Python :: 3.8
Classifier: Programming Language :: Python :: 3.9
Classifier: Programming Language :: Python :: 3.10
Classifier: Programming Language :: Python :: 3.11
Classifier: Programming Language :: Python :: 3.12
Classifier: Topic :: Multimedia :: Video :: Conversion
Requires-Python: >=3.8
License-File: LICENSE
Requires-Dist: moviepy>=1.0.0
Requires-Dist: customtkinter>=5.0.0
Requires-Dist: yt-dlp
Requires-Dist: imageio-ffmpeg
Provides-Extra: dev
Requires-Dist: pytest; extra == "dev"
Requires-Dist: pytest-mock; extra == "dev"
Requires-Dist: pytest-cov; extra == "dev"
Requires-Dist: pytest-xdist; extra == "dev"
Dynamic: license-file
